yxmb_compatlib/__init__.py
yxmb_compatlib/_pyinstaller.py
yxmb_compatlib/comment/check_element.py
yxmb_compatlib/comment/check_excel_last.py
yxmb_compatlib/comment/check_existing_data.py
yxmb_compatlib/comment/disable_login_bg.py
yxmb_compatlib/comment/envWrite.py
yxmb_compatlib/comment/excel_write.py
yxmb_compatlib/comment/excle_create.py
yxmb_compatlib/comment/excle_write.py
yxmb_compatlib/comment/file_create.py
yxmb_compatlib/comment/folder_create.py
yxmb_compatlib/comment/format_value.py
yxmb_compatlib/comment/id_Verification.py
yxmb_compatlib/comment/is_iso_8601.py
yxmb_compatlib/comment/logger.py
yxmb_compatlib/comment/login_account.py
yxmb_compatlib/comment/lz.py
yxmb_compatlib/comment/phone_Verification.py
yxmb_compatlib/comment/rqbaoc.py
yxmb_compatlib/comment/write_excle.py
yxmb_compatlib/comment/到期.py
yxmb_compatlib/comment/登录头.py
yxmb_compatlib/compements/assemblies/check_diseases.py
yxmb_compatlib/compements/assemblies/check_sf_date.py
yxmb_compatlib/compements/assemblies/check_sf_date_same_day.py
yxmb_compatlib/compements/assemblies/get_mb_data.py
yxmb_compatlib/compements/assemblies/get_mz_data.py
yxmb_compatlib/compements/assemblies/get_new_sf_data.py
yxmb_compatlib/compements/assemblies/get_new_sf_date.py
yxmb_compatlib/compements/assemblies/get_sf_data.py
yxmb_compatlib/compements/assemblies/get_tj_data.py
yxmb_compatlib/compements/assemblies/has_current_quarter.py
yxmb_compatlib/compements/new_assessment.py
yxmb_compatlib/compements/quarterly_statistics.py
yxmb_compatlib/compements/tool.py
yxmb_compatlib/compements/whether_assessment.py
yxmb_compatlib/config/__init__.py
yxmb_compatlib/config/hospital_name.py
yxmb_compatlib/config/load_config.py
yxmb_compatlib/config/path.py
yxmb_compatlib/hooks/hook-yxmb_compatlib.py
yxmb_compatlib/hospital_config/default.toml
yxmb_compatlib/hospital_config/南苑.toml
yxmb_compatlib/hospital_config/广宁.toml
yxmb_compatlib/hospital_config/永宁.toml
yxmb_compatlib/hospital_config/潞城.toml
yxmb_compatlib-2025.8.5.0.dist-info/WHEEL
yxmb_compatlib-2025.8.5.0.dist-info/entry_points.txt
yxmb_compatlib-2025.8.5.0.dist-info/METADATA
yxmb_compatlib-2025.8.5.0.dist-info/RECORD
