Metadata-Version: 2.3
Name: yxmb-compatlib
Version: 2025.8.5.0
Summary: 支持原地升级的宇信慢病兼容库
Author: Maple
Author-email: Maple <wjxa20152015@gmail.com>
Requires-Dist: ddddocr>=1.5.6
Requires-Dist: openpyxl>=3.1.5
Requires-Dist: pandas>=2.3.1
Requires-Dist: phis-config>=2025.8.1.0
Requires-Dist: pyinstaller>=6.14.2
Requires-Dist: selenium>=4.34.2
Requires-Python: >=3.12
